mfd_devcon/__init__.py
mfd_devcon/base.py
mfd_devcon/exceptions.py
mfd_devcon/parser.py
mfd_devcon-2.0.0.dist-info/licenses/AUTHORS.md
mfd_devcon-2.0.0.dist-info/licenses/LICENSE.md
mfd_devcon-2.0.0.dist-info/METADATA
mfd_devcon-2.0.0.dist-info/WHEEL
mfd_devcon-2.0.0.dist-info/top_level.txt
mfd_devcon-2.0.0.dist-info/RECORD
