Metadata-Version: 2.4
Name: mfd-devcon
Version: 2.0.0
Summary: Module providing a programmatic interface to Windows Devcon device management commands.
Project-URL: Homepage, https://github.com/intel/mfd
Project-URL: Repository, https://github.com/intel/mfd-devcon
Project-URL: Issues, https://github.com/intel/mfd-devcon/issues
Project-URL: Changelog, https://github.com/intel/mfd-devcon/blob/main/CHANGELOG.md
Requires-Python: <3.14,>=3.10
License-File: LICENSE.md
License-File: AUTHORS.md
Requires-Dist: mfd-base-tool>=2.7.0
Requires-Dist: mfd-common-libs>=1.11.0
Requires-Dist: mfd-connect>=7.12.0
Requires-Dist: mfd-typing>=1.23.0
Dynamic: license-file
